{"action":{"identity":{"address":"N\u0000sourcecred\u0000core\u0000IDENTITY\u0000dJM2FWN1DT0OpFmkuPAFqg\u0000","aliases":[],"id":"dJM2FWN1DT0OpFmkuPAFqg","name":"phi-dao","subtype":"USER"},"type":"CREATE_IDENTITY"},"ledgerTimestamp":1610950493488,"uuid":"vGVSDaFJRfEOBBfET5Msvw","version":"1"}
{"action":{"alias":{"address":"N\u0000sourcecred\u0000github\u0000USERLIKE\u0000USER\u0000phi-dao\u0000","description":"github/[@phi-dao](https://github.com/phi-dao)"},"identityId":"dJM2FWN1DT0OpFmkuPAFqg","type":"ADD_ALIAS"},"ledgerTimestamp":1610950493488,"uuid":"NWpHkOiviK8ZYAmRrovUVw","version":"1"}
{"action":{"identity":{"address":"N\u0000sourcecred\u0000core\u0000IDENTITY\u00002W7NCbT4ezWBmKQg4vNxzw\u0000","aliases":[],"id":"2W7NCbT4ezWBmKQg4vNxzw","name":"SourceCred","subtype":"PROJECT"},"type":"CREATE_IDENTITY"},"ledgerTimestamp":1610950493494,"uuid":"LnPMOTy8IDcWR0vqI4uPgA","version":"1"}
{"action":{"identityId":"2W7NCbT4ezWBmKQg4vNxzw","type":"TOGGLE_ACTIVATION"},"ledgerTimestamp":1610950493496,"uuid":"zHLRlIPZECW404LzMv3S5A","version":"1"}
{"action":{"identity":{"address":"N\u0000sourcecred\u0000core\u0000IDENTITY\u0000YrAKYAWRTdB3SjPuajObDQ\u0000","aliases":[],"id":"YrAKYAWRTdB3SjPuajObDQ","name":"dependabot","subtype":"BOT"},"type":"CREATE_IDENTITY"},"ledgerTimestamp":1614730875406,"uuid":"qJG98BfvTN4EWD34eE8fyA","version":"1"}
{"action":{"alias":{"address":"N\u0000sourcecred\u0000github\u0000USERLIKE\u0000BOT\u0000dependabot\u0000","description":"github/[@dependabot](https://github.com/apps/dependabot)"},"identityId":"YrAKYAWRTdB3SjPuajObDQ","type":"ADD_ALIAS"},"ledgerTimestamp":1614730875407,"uuid":"RIV0H4dSLoAy3pHxQgEpcw","version":"1"}
{"action":{"identity":{"address":"N\u0000sourcecred\u0000core\u0000IDENTITY\u00004qTldjck5iBYvwFl9wfDWA\u0000","aliases":[],"id":"4qTldjck5iBYvwFl9wfDWA","name":"github-actions","subtype":"BOT"},"type":"CREATE_IDENTITY"},"ledgerTimestamp":1614730875408,"uuid":"Q4ZKJYEt91eilSV99l3MJA","version":"1"}
{"action":{"alias":{"address":"N\u0000sourcecred\u0000github\u0000USERLIKE\u0000BOT\u0000github-actions\u0000","description":"github/[@github-actions](https://github.com/apps/github-actions)"},"identityId":"4qTldjck5iBYvwFl9wfDWA","type":"ADD_ALIAS"},"ledgerTimestamp":1614730875408,"uuid":"hwuGuRQ62j9vJ7C4ydSPfg","version":"1"}
